classes/__init__.py
classes/address.py
classes/address_book.py
classes/birthday.py
classes/email.py
classes/field.py
classes/name.py
classes/note.py
classes/notes_book.py
classes/phone.py
classes/record.py
classes/tag.py
constants/__init__.py
constants/assistant_info.py
constants/auto_complete_cl.py
handlers/__init__.py
handlers/birthday_handlers.py
handlers/contacts_handlers.py
handlers/decorators.py
handlers/notes_handlers.py
handlers/parse_input.py
handlers/validations.py
helpers/__init__.py
helpers/assistant_info.py
helpers/autocomplete_config.py
helpers/logging_config.py
helpers/notes_pickle_utils.py
helpers/pickle_utils.py
helpers/startup_shutdown.py
no_name_bot/__init__.py
no_name_bot/main.py
no_name_bot-1.8.dist-info/METADATA
no_name_bot-1.8.dist-info/WHEEL
no_name_bot-1.8.dist-info/entry_points.txt
no_name_bot-1.8.dist-info/top_level.txt
no_name_bot-1.8.dist-info/RECORD
